pika-stubs/METADATA.toml
pika-stubs/__init__.pyi
pika-stubs/amqp_object.pyi
pika-stubs/callback.pyi
pika-stubs/channel.pyi
pika-stubs/compat.pyi
pika-stubs/connection.pyi
pika-stubs/credentials.pyi
pika-stubs/data.pyi
pika-stubs/delivery_mode.pyi
pika-stubs/diagnostic_utils.pyi
pika-stubs/exceptions.pyi
pika-stubs/exchange_type.pyi
pika-stubs/frame.pyi
pika-stubs/heartbeat.pyi
pika-stubs/py.typed
pika-stubs/spec.pyi
pika-stubs/tcp_socket_opts.pyi
pika-stubs/validators.pyi
pika-stubs/adapters/__init__.pyi
pika-stubs/adapters/asyncio_connection.pyi
pika-stubs/adapters/base_connection.pyi
pika-stubs/adapters/blocking_connection.pyi
pika-stubs/adapters/gevent_connection.pyi
pika-stubs/adapters/select_connection.pyi
pika-stubs/adapters/tornado_connection.pyi
pika-stubs/adapters/twisted_connection.pyi
pika-stubs/adapters/utils/__init__.pyi
pika-stubs/adapters/utils/connection_workflow.pyi
pika-stubs/adapters/utils/io_services_utils.pyi
pika-stubs/adapters/utils/nbio_interface.pyi
pika-stubs/adapters/utils/selector_ioloop_adapter.pyi
types_pika_ts-1.3.0.20250822.dist-info/licenses/LICENSE
types_pika_ts-1.3.0.20250822.dist-info/METADATA
types_pika_ts-1.3.0.20250822.dist-info/WHEEL
types_pika_ts-1.3.0.20250822.dist-info/top_level.txt
types_pika_ts-1.3.0.20250822.dist-info/RECORD
